dash_intersection_observer/DashIntersectionObserver.py
dash_intersection_observer/__init__.py
dash_intersection_observer/_imports_.py
dash_intersection_observer/dash_intersection_observer.js
dash_intersection_observer/metadata.json
dash_intersection_observer/package-info.json
dash_intersection_observer-1.0.1.dist-info/LICENSE
dash_intersection_observer-1.0.1.dist-info/METADATA
dash_intersection_observer-1.0.1.dist-info/WHEEL
dash_intersection_observer-1.0.1.dist-info/top_level.txt
dash_intersection_observer-1.0.1.dist-info/RECORD
