Metadata-Version: 2.1
Name: dash-intersection-observer
Version: 1.0.1
Summary: Intersection Observer for Dash
Author: Renaud Lainé <Enter your email (For package.json)>
License: MIT
Classifier: Framework :: Dash
License-File: LICENSE
